ae_automation/__init__.py
ae_automation/client.py
ae_automation/settings.py
ae_automation/mixins/VideoEditorApp.py
ae_automation/mixins/__init__.py
ae_automation/mixins/afterEffect.py
ae_automation/mixins/bot.py
ae_automation/mixins/processManager.py
ae_automation/mixins/templateGenerator.py
ae_automation/mixins/tools.py
ae_automation/mixins/types.py
ae_automation/mixins/js/addComp.jsx
ae_automation/mixins/js/add_comp_to_templates.jsx
ae_automation/mixins/js/add_marker.jsx
ae_automation/mixins/js/add_null_layer.jsx
ae_automation/mixins/js/add_resource.jsx
ae_automation/mixins/js/add_shape_layer.jsx
ae_automation/mixins/js/add_solid_layer.jsx
ae_automation/mixins/js/add_text_layer.jsx
ae_automation/mixins/js/ae_command_runner.jsx
ae_automation/mixins/js/ae_server.jsx
ae_automation/mixins/js/checkIfItemExists.jsx
ae_automation/mixins/js/check_scripting_enabled.jsx
ae_automation/mixins/js/create_folder.jsx
ae_automation/mixins/js/create_new_project.jsx
ae_automation/mixins/js/debug_create_comp.jsx
ae_automation/mixins/js/duplicate_comp.jsx
ae_automation/mixins/js/duplicate_comp_1.jsx
ae_automation/mixins/js/duplicate_comp_2.jsx
ae_automation/mixins/js/file_map.jsx
ae_automation/mixins/js/framework.js
ae_automation/mixins/js/getMarker.jsx
ae_automation/mixins/js/importFile.jsx
ae_automation/mixins/js/json2.js
ae_automation/mixins/js/openItemName.jsx
ae_automation/mixins/js/renameItem.jsx
ae_automation/mixins/js/renderComp.jsx
ae_automation/mixins/js/run_command.jsx
ae_automation/mixins/js/save_project.jsx
ae_automation/mixins/js/selectItem.jsx
ae_automation/mixins/js/selectItemByName.jsx
ae_automation/mixins/js/selectItemLayer.jsx
ae_automation/mixins/js/selectLayerByIndex.jsx
ae_automation/mixins/js/selectLayerByLayer.jsx
ae_automation/mixins/js/update_properties.jsx
ae_automation/mixins/js/update_properties_frame.jsx
ae_automation/mixins/js/update_resource.jsx
ae_automation/mixins/js/workAreaComp.jsx
ae_automation/mixins/videoEditor/dist/index.html
after_effects_automation-0.1.3.dist-info/licenses/LICENSE
after_effects_automation-0.1.3.dist-info/METADATA
after_effects_automation-0.1.3.dist-info/WHEEL
after_effects_automation-0.1.3.dist-info/entry_points.txt
after_effects_automation-0.1.3.dist-info/top_level.txt
after_effects_automation-0.1.3.dist-info/RECORD
