Metadata-Version: 2.4
Name: after-effects-automation
Version: 0.1.3
Summary: A Python tool for automating Adobe After Effects workflows
Home-page: https://github.com/jhd3197/after-effects-automation
Author: Juan Denis
Author-email: juan@vene.co
Classifier: Development Status :: 3 - Alpha
Classifier: Intended Audience :: Developers
Classifier: Topic :: Multimedia :: Video
Classifier: Programming Language :: Python :: 3
Classifier: Programming Language :: Python :: 3.7
Classifier: Programming Language :: Python :: 3.8
Classifier: Programming Language :: Python :: 3.9
Classifier: License :: OSI Approved :: MIT License
Classifier: Operating System :: Microsoft :: Windows
Requires-Python: >=3.7
License-File: LICENSE
Requires-Dist: python-dotenv>=0.19.0
Requires-Dist: pyautogui>=0.9.53
Requires-Dist: pydirectinput>=1.0.4
Requires-Dist: pywinauto>=0.6.8
Requires-Dist: pandas>=1.3.0
Requires-Dist: pydantic>=1.8.2
Requires-Dist: jsmin>=3.0.0
Requires-Dist: mutagen>=1.45.1
Requires-Dist: moviepy>=1.0.3
Requires-Dist: flask>=2.0.0
Requires-Dist: flask-cors>=3.0.0
Requires-Dist: werkzeug>=2.0.0
Requires-Dist: psutil>=5.8.0
Dynamic: author
Dynamic: author-email
Dynamic: classifier
Dynamic: description
Dynamic: description-content-type
Dynamic: home-page
Dynamic: license-file
Dynamic: requires-dist
Dynamic: requires-python
Dynamic: summary
